document_reader/__init__.py
document_reader/dependencies.py
document_reader/main.py
document_reader/path.py
document_reader-0.1.0.dist-info/LICENSE
document_reader-0.1.0.dist-info/METADATA
document_reader-0.1.0.dist-info/WHEEL
document_reader-0.1.0.dist-info/top_level.txt
document_reader-0.1.0.dist-info/RECORD
