Metadata-Version: 2.1
Name: document-reader
Version: 0.1.0
Summary: Read several document format to output a markdown like python string
Home-page: https://github.com/joris-philippoteaux-BE/document_reader.git
Author: Joris PHILIPPOTEAUX
Author-email: joris.philippoteaux@bearingpoint.com
Classifier: Programming Language :: Python :: 3.11
License-File: LICENSE
